{
  "key": "group_63c9c40268d07",
  "title": "F+T Block: Navigation",
  "fields": [
    {
      "key": "field_63c9c4022eb35",
      "label": "Menu Location",
      "name": "menu_location",
      "aria-label": "",
      "type": "text",
      "instructions": "",
      "required": 0,
      "conditional_logic": 0,
      "wrapper": {
        "width": "",
        "class": "",
        "id": ""
      },
      "default_value": "primary",
      "maxlength": "",
      "placeholder": "",
      "prepend": "",
      "append": ""
    }
  ],
  "location": [
    [
      {
        "param": "block",
        "operator": "==",
        "value": "ft/navigation"
      }
    ]
  ],
  "menu_order": 0,
  "position": "normal",
  "style": "default",
  "label_placement": "left",
  "instruction_placement": "label",
  "hide_on_screen": "",
  "active": true,
  "description": "",
  "show_in_rest": 0,
  "acfe_display_title": "",
  "acfe_autosync": ["json"],
  "acfe_form": 0,
  "acfe_meta": "",
  "acfe_note": ""
}
